[{"content":"安裝java 安装 mysql 5.7 安裝 jira 破解 confluence 同步 用户数据 在jira 中添加用户服务器：用户管理 \u0026mdash 用户服务器 创建一个 中添加白名单，并允许传入 eg 在confluence中配置对应的链接：用户目录 添加目录 atlassian 插件破解 查看破解参数： java -jar root atlassian-agent.jar 第三方插件将其应用密钥 插件关键字作为参数。如： -s 是jira 的服务器id 通知方案 （不要用邮件通知、用插件 notifications 桌面通知） google 生产 killliu@163.com app password zrrhsmbeadyuggri 配置黑名单 nginx 代理","date":"2022-05-16","description":null,"permalink":"https://note.killliu.com/notes/jira/","tags":["centos"],"title":"jira in centos"},{"content":"配置 github 新建仓库 killliu.github.io 点击新仓库的 settings 页签中的 pages，设置自定义域名：note.killliu.com save 配置域名 dns 管理配置中增加一条记录 类型 名称 资料 cname note 安装 hugo 拉取仓库 git clone cd 到该目录内，创建 项目 app 后，将其目录内的所有文件移动到上一层，删除 目录 new site 添加主题 修改配置文件 config.toml 以指定主题 echo \u0026rsquotheme color-your-world\u0026rsquo \u0026raquo 添加文章 posts hugo_github_blog.md \u0026mdash 注意 \u0026mdash：draft草稿 对应的值要改为 false 才会被生成静态页面 打包网页 -d docs 本地预览 server pages 找到 source 选择","date":"2022-05-15","description":"A smalll description","permalink":"https://note.killliu.com/notes/hugo_github_blog/","tags":["tools"],"title":"搭建 github + hugo 博客 (macos)"}]